maskalib/__init__.py
maskalib/tiktokmaskao.py
maskalib-3.8.dist-info/METADATA
maskalib-3.8.dist-info/WHEEL
maskalib-3.8.dist-info/top_level.txt
maskalib-3.8.dist-info/RECORD
