Metadata-Version: 2.1
Name: maskalib
Version: 3.8
